rag_mongo_logger/__init__.py
rag_mongo_logger/context_logging.py
rag_mongo_logger/handlers.py
rag_mongo_logger/logger_setup.py
rag_mongo_logger/singleton.py
rag_mongo_logger-0.1.4.dist-info/licenses/LICENSE
rag_mongo_logger-0.1.4.dist-info/METADATA
rag_mongo_logger-0.1.4.dist-info/WHEEL
rag_mongo_logger-0.1.4.dist-info/top_level.txt
rag_mongo_logger-0.1.4.dist-info/RECORD
